origin_ledger_sdk/__init__.py
origin_ledger_sdk/batch.py
origin_ledger_sdk/ledger_connector.py
origin_ledger_sdk/ledger_dto/__init__.py
origin_ledger_sdk/ledger_dto/enums.py
origin_ledger_sdk/ledger_dto/helpers.py
origin_ledger_sdk/ledger_dto/models.py
origin_ledger_sdk/ledger_dto/requests.py
origin_ledger_sdk/requests/__init__.py
origin_ledger_sdk/requests/abstract_request.py
origin_ledger_sdk/requests/helpers.py
origin_ledger_sdk/requests/issue_ggo_request.py
origin_ledger_sdk/requests/publish_measurement_request.py
origin_ledger_sdk/requests/retire_ggo_request.py
origin_ledger_sdk/requests/split_ggo_request.py
origin_ledger_sdk/requests/transfer_ggo_request.py
Origin_Ledger_SDK-1.0.20.dist-info/LICENSE
Origin_Ledger_SDK-1.0.20.dist-info/METADATA
Origin_Ledger_SDK-1.0.20.dist-info/WHEEL
Origin_Ledger_SDK-1.0.20.dist-info/top_level.txt
Origin_Ledger_SDK-1.0.20.dist-info/RECORD
