Metadata-Version: 2.1
Name: Origin-Ledger-SDK
Version: 1.0.20
Summary: Project Origin ledger SDK
Home-page: https://github.com/project-origin/ledger-sdk-python
Author: Martin Schmidt
Author-email: mcs@energinet.dk
License: UNKNOWN
Platform: UNKNOWN
Classifier: Development Status :: 3 - Alpha
Classifier: Programming Language :: Python :: 3
Classifier: License :: OSI Approved :: MIT License
Classifier: Operating System :: POSIX :: Linux
Requires-Python: >=3.7
Requires-Dist: requests
Requires-Dist: sawtooth-sdk (==1.2.3)
Requires-Dist: marshmallow-dataclass
Requires-Dist: marshmallow-enum
